rgb_lib/__init__.py
rgb_lib/_rgb_lib/__init__.py
rgb_lib/_rgb_lib/librgblibffi.so
rgb_lib/_rgb_lib/rgb_lib.py
rgb_lib-0.2.0.dist-info/METADATA
rgb_lib-0.2.0.dist-info/WHEEL
rgb_lib-0.2.0.dist-info/RECORD
