Metadata-Version: 2.1
Name: rgb-lib
Version: 0.2.0
Summary: RGB Lib Python language bindings.
Home-page: https://github.com/RGB-Tools/rgb-lib-python
License: MIT
Keywords: rgb,bitcoin
Author: Zoe Faltibà
Author-email: zoefaltiba@gmail.com
Requires-Python: >=3.9.0,<4.0.0
Classifier: Development Status :: 4 - Beta
Classifier: Intended Audience :: Developers
Classifier: License :: OSI Approved :: MIT License
Classifier: Natural Language :: English
Classifier: Operating System :: MacOS
Classifier: Operating System :: POSIX :: Linux
Classifier: Programming Language :: Python :: 3
Classifier: Programming Language :: Python :: 3.9
Classifier: Programming Language :: Python :: 3.10
Classifier: Programming Language :: Python :: 3.11
Classifier: Topic :: Other/Nonlisted Topic
Project-URL: Documentation, https://github.com/RGB-Tools/rgb-lib-python
Project-URL: Repository, https://github.com/RGB-Tools/rgb-lib-python
